setup.py
distributions_probability_dyy/Binomialdistribution.py
distributions_probability_dyy/Gaussiandistribution.py
distributions_probability_dyy/Generaldistribution.py
distributions_probability_dyy/__init__.py
distributions_probability_dyy.egg-info/PKG-INFO
distributions_probability_dyy.egg-info/SOURCES.txt
distributions_probability_dyy.egg-info/dependency_links.txt
distributions_probability_dyy.egg-info/not-zip-safe
distributions_probability_dyy.egg-info/top_level.txt