Metadata-Version: 1.0
Name: distributions-probability-dyy
Version: 1.1
Summary: Gaussian distribution
Home-page: UNKNOWN
Author: Daniela Yassuda Yamashita
Author-email: UNKNOWN
License: UNKNOWN
Platform: UNKNOWN
